demo/__init__.py
demo/conf.py
demo/delete_msg.py
demo/hello_app.py
demo/hello_cuids.py
demo/hello_pushids.py
sppush/__init__.py
sppush/sdk.py
sppush-1.0.4.dist-info/METADATA
sppush-1.0.4.dist-info/RECORD
sppush-1.0.4.dist-info/WHEEL
sppush-1.0.4.dist-info/top_level.txt
